amukhsimov_jupyter_templates_bigdata.py
amukhsimov_jupyter_templates_bigdata/__init__.py
amukhsimov_jupyter_templates_bigdata/connectors.py
amukhsimov_jupyter_templates_bigdata/crypto.py
amukhsimov_jupyter_templates_bigdata/functions.py
amukhsimov_jupyter_templates_bigdata-0.0.10.dist-info/METADATA
amukhsimov_jupyter_templates_bigdata-0.0.10.dist-info/WHEEL
amukhsimov_jupyter_templates_bigdata-0.0.10.dist-info/top_level.txt
amukhsimov_jupyter_templates_bigdata-0.0.10.dist-info/RECORD
