Metadata-Version: 2.1
Name: amukhsimov-jupyter-templates-bigdata
Version: 0.0.10
Summary: amukhsimov-jupyter-templates-bigdata
Author: Akmal Mukhsimov
Author-email: a.mukhsimov@hamkorlab.club
License: UNKNOWN
Platform: UNKNOWN
Classifier: Programming Language :: Python :: 3
Classifier: License :: OSI Approved :: MIT License
Classifier: Operating System :: OS Independent
Requires-Python: >=3.6
Requires-Dist: python-dotenv
Requires-Dist: pyspark
Requires-Dist: cx-Oracle
Requires-Dist: cryptography
Requires-Dist: psycopg2
